<?xml version="1.0" encoding="utf-8" ?>
<widget id="loves.nativetextinputautofocus.NativeTextInputAutoFocus" pluginWidget="true" needsEntityContext="true" offlineCapable="true"
        supportedPlatform="Native"
        xmlns="http://www.mendix.com/widget/1.0/" xmlns:xsi="http://www.w3.org/2001/XMLSchema-instance"
        xsi:schemaLocation="http://www.mendix.com/widget/1.0/ ../node_modules/mendix/custom_widget.xsd">
    <name>Native Text Input Auto Focus</name>
    <description>React Native TextInput field that grabs focus on page load and hides keyboard</description>
    <icon/>
    <properties>
        <propertyGroup caption="General">
            <property key="valueAttribute" type="attribute" required="false" onChange="onChangeAction">
                <caption>Value attribute</caption>
                <description>The attribute that contains the value</description>
                <attributeTypes>
                    <attributeType name="Long" />
                </attributeTypes>
            </property>
            <property key="placeholderText" type="string" required="false">
                <caption>Placeholder Text</caption>
                <description>Appears in input field until something entered</description>
            </property>
            <property key="minLength" type="integer" defaultValue="14" required="true">
                <caption>Minimum Length</caption>
                <description>Will not update attribute until this length is received</description>
            </property>
        </propertyGroup>
        <propertyGroup caption="Events">
            <property key="onChangeAction" type="action" required="true">
                <caption>On change</caption>
                <description />
            </property>
        </propertyGroup>
    </properties>
</widget>
